[
	{
		"id":"0001",
		"title":"韩妙我的美丽日记牛奶美白润肤面膜10片装",
		"priced":"14.9",
		"price":"29.00",
		"imgres":"pa1.jpg",
		"sale_num":"296"
	},
	{
		"id":"0002",
		"title":"ALOBON雅邦 3D裸妆BB霜40ml 2#自然色",
		"priced":"14.9",
		"price":"29.00",
		"imgres":"pa2.jpg",
		"sale_num":"296"
	},
	{
		"id":"0003",
		"title":"MISSHA谜尚四重功效红色BB霜50ml21#SPF42",
		"priced":"14.9",
		"price":"29.00",
		"imgres":"pa3.jpg",
		"sale_num":"296"
	},
	{
		"id":"0004",
		"title":"自然堂活泉控油细毛孔精华霜（BB霜）35ml",
		"priced":"14.9",
		"price":"29.00",
		"imgres":"pa4.jpg",
		"sale_num":"296"
	},
	{
		"id":"0005",
		"title":"MISSHA谜尚四重功效红色BB霜50ml21#SPF42",
		"priced":"14.9",
		"price":"29.00",
		"imgres":"pa5.jpg",
		"sale_num":"296"
	},
	{
		"id":"0006",
		"title":"韩妙我的美丽日记牛奶美白润肤面膜10片装",
		"priced":"14.9",
		"price":"29.00",
		"imgres":"pa6.jpg",
		"sale_num":"296"
	},
	{
		"id":"0007",
		"title":"百雀羚草本水嫩精纯明星BB霜40g",
		"priced":"14.9",
		"price":"29.00",
		"imgres":"pa7.jpg",
		"sale_num":"296"
	},
	{
		"id":"0008",
		"title":"MISSHA谜尚四重功效红色BB霜50ml21#SPF42",
		"priced":"14.9",
		"price":"29.00",
		"imgres":"pa8.jpg",
		"sale_num":"296"
	},
	{
		"id":"0009",
		"title":"韩妙我的美丽日记牛奶美白润肤面膜10片装",
		"priced":"14.9",
		"price":"29.00",
		"imgres":"pa9.jpg",
		"sale_num":"296"
	},
	{
		"id":"0010",
		"title":"自然堂活泉控油细毛孔精华霜（BB霜）35ml",
		"priced":"14.9",
		"price":"29.00",
		"imgres":"pa10.jpg",
		"sale_num":"296"
	},
	{
		"id":"0011",
		"title":"MISSHA谜尚四重功效红色BB霜50ml21#SPF42",
		"priced":"14.9",
		"price":"29.00",
		"imgres":"pa11.jpg",
		"sale_num":"296"
	},
	{
		"id":"0012",
		"title":"百雀羚草本水嫩精纯明星BB霜40g",
		"priced":"11.9",
		"price":"29.00",
		"imgres":"pa12.jpg",
		"sale_num":"296"
	},
	{
		"id":"0013",
		"title":"韩妙我的美丽日记牛奶美白润肤面膜10片装",
		"priced":"14.9",
		"price":"29.00",
		"imgres":"pa13.jpg",
		"sale_num":"296"
	},
	{
		"id":"0014",
		"title":"韩妙我的美丽日记牛奶美白润肤面膜10片装",
		"priced":"14.9",
		"price":"29.00",
		"imgres":"pa14.jpg",
		"sale_num":"296"
	},
	{
		"id":"0015",
		"title":"MISSHA谜尚四重功效红色BB霜50ml21#SPF42",
		"priced":"14.9",
		"price":"29.00",
		"imgres":"pa15.jpg",
		"sale_num":"296"
	},
	{
		"id":"0016",
		"title":"自然堂活泉控油细毛孔精华霜（BB霜）35ml",
		"priced":"14.9",
		"price":"29.00",
		"imgres":"pa16.jpg",
		"sale_num":"296"
	},
	{
		"id":"0017",
		"title":"百雀羚草本水嫩精纯明星BB霜40g",
		"priced":"14.9",
		"price":"29.00",
		"imgres":"pa17.jpg",
		"sale_num":"296"
	},
	{
		"id":"0018",
		"title":"韩妙我的美丽日记牛奶美白润肤面膜10片装",
		"priced":"34.9",
		"price":"23.00",
		"imgres":"pa18.jpg",
		"sale_num":"3296"
	},
	{
		"id":"0019",
		"title":"MISSHA谜尚四重功效红色BB霜50ml21#SPF42",
		"priced":"54.9",
		"price":"42.00",
		"imgres":"pa19.jpg",
		"sale_num":"24296"
	},
	{
		"id":"0020",
		"title":"韩妙我的美丽日记牛奶美白润肤面膜10片装",
		"priced":"33.9",
		"price":"55.00",
		"imgres":"pa20.jpg",
		"sale_num":"24396"
	},
	{
		"id":"0021",
		"title":"自然堂活泉控油细毛孔精华霜（BB霜）35ml",
		"priced":"24.9",
		"price":"24.00",
		"imgres":"pa21.jpg",
		"sale_num":"4496"
	},
	{
		"id":"0022",
		"title":"百雀羚草本水嫩精纯明星BB霜40g",
		"priced":"15.3",
		"price":"4.00",
		"imgres":"pa22.jpg",
		"sale_num":"2946"
	},
	{
		"id":"0023",
		"title":"MISSHA谜尚四重功效红色BB霜50ml21#SPF42",
		"priced":"14.9",
		"price":"29.00",
		"imgres":"pa1.jpg",
		"sale_num":"296"
	},
	{
		"id":"0024",
		"title":"韩妙我的美丽日记牛奶美白润肤面膜10片装",
		"priced":"14.9",
		"price":"29.00",
		"imgres":"pa2.jpg",
		"sale_num":"296"
	},
	{
		"id":"0025",
		"title":"自然堂活泉控油细毛孔精华霜（BB霜）35ml",
		"priced":"14.9",
		"price":"29.00",
		"imgres":"pa3.jpg",
		"sale_num":"296"
	},
	{
		"id":"0026",
		"title":"MISSHA谜尚四重功效红色BB霜50ml21#SPF42",
		"priced":"14.9",
		"price":"29.00",
		"imgres":"pa4.jpg",
		"sale_num":"296"
	},
	{
		"id":"0027",
		"title":"百雀羚草本水嫩精纯明星BB霜40g",
		"priced":"14.9",
		"price":"29.00",
		"imgres":"pa5.jpg",
		"sale_num":"296"
	},
	{
		"id":"0028",
		"title":"韩妙我的美丽日记牛奶美白润肤面膜10片装",
		"priced":"14.9",
		"price":"29.00",
		"imgres":"pa6.jpg",
		"sale_num":"296"
	},
	{
		"id":"0029",
		"title":"自然堂活泉控油细毛孔精华霜（BB霜）35ml",
		"priced":"14.9",
		"price":"29.00",
		"imgres":"pa7.jpg",
		"sale_num":"296"
	},
	{
		"id":"0030",
		"title":"百雀羚草本水嫩精纯明星BB霜40g",
		"priced":"14.9",
		"price":"29.00",
		"imgres":"pa8.jpg",
		"sale_num":"296"
	},
	{
		"id":"0031",
		"title":"韩妙我的美丽日记牛奶美白润肤面膜10片装",
		"priced":"14.9",
		"price":"29.00",
		"imgres":"pa9.jpg",
		"sale_num":"296"
	},
	{
		"id":"0032",
		"title":"自然堂活泉控油细毛孔精华霜（BB霜）35ml",
		"priced":"14.9",
		"price":"29.00",
		"imgres":"pa10.jpg",
		"sale_num":"296"
	},
	{
		"id":"0033",
		"title":"MISSHA谜尚四重功效红色BB霜50ml21#SPF42",
		"priced":"14.9",
		"price":"29.00",
		"imgres":"pa11.jpg",
		"sale_num":"296"
	},
	{
		"id":"0034",
		"title":"百雀羚草本水嫩精纯明星BB霜40g",
		"priced":"14.9",
		"price":"29.00",
		"imgres":"pa12.jpg",
		"sale_num":"296"
	}
]
